sufsd/By.py
sufsd/__init__.py
sufsd/log.py
sufsd/utils.py
sufsd-0.8.2.dist-info/METADATA
sufsd-0.8.2.dist-info/WHEEL
sufsd-0.8.2.dist-info/top_level.txt
sufsd-0.8.2.dist-info/RECORD
